{
  "pageProps": {
    "posts": [
      {
        "title": "Things I Keep Forgetting - Behavior in PR from Forked Repository in Github",
        "date": "2023-09-03T00:00:00.000Z",
        "tags": ["Github", "OSS", "Git"],
        "draft": false,
        "summary": "Getting a Pull Request (PR) from a Forked Repository in Github can be quite confusing. Here I put a note to self about the behavior that apparantly I keep forgetting.",
        "slug": "things-i-keep-forgetting-github-forked"
      },
      {
        "title": "My Git Aliases",
        "date": "2021-05-30T07:16:50.000Z",
        "draft": false,
        "category": "Tech",
        "tags": ["Git", "CLI"],
        "summary": "My Git aliases that I use on daily basis to help me with works and make Git more interactive and efficient",
        "ogimage": "./1.gif",
        "slug": "my-git-alias"
      }
    ],
    "tag": "git"
  },
  "__N_SSG": true
}
